CHANGELOG.md
qstone/__init__.py
qstone/__main__.py
qstone/apps/PyMatching.py
qstone/apps/QBC.py
qstone/apps/RB.py
qstone/apps/VQE.py
qstone/apps/__init__.py
qstone/apps/computation.py
qstone/circuits/syndrome_extraction.qasm
qstone/connectors/__init__.py
qstone/connectors/backends/__init__.py
qstone/connectors/backends/rigetti/__init__.py
qstone/connectors/backends/rigetti/runner.py
qstone/connectors/connection.py
qstone/connectors/connector.py
qstone/connectors/grpc/README.md
qstone/connectors/grpc/__init__.py
qstone/connectors/grpc/qpu.proto
qstone/connectors/grpc/qpu_pb2.py
qstone/connectors/grpc/qpu_pb2_grpc.py
qstone/connectors/grpc/runner.py
qstone/connectors/http/__init__.py
qstone/connectors/http/runner.py
qstone/connectors/no_link/__init__.py
qstone/connectors/no_link/no_link.py
qstone/generators/__init__.py
qstone/generators/bare_metal/__init__.py
qstone/generators/bare_metal/initialise.sh
qstone/generators/bare_metal/type_exec_{app}.sh.jinja
qstone/generators/common/jobs.py.jinja
qstone/generators/common/qstone.sh.jinja
qstone/generators/common/type_exec.py.jinja
qstone/generators/generator.py
qstone/generators/lsf/__init__.py
qstone/generators/lsf/jsrun/__init__.py
qstone/generators/lsf/jsrun/initialise.sh
qstone/generators/lsf/jsrun/type_exec_{app}.bsub.jinja
qstone/generators/slurm/__init__.py
qstone/generators/slurm/schedmd/__init__.py
qstone/generators/slurm/schedmd/initialise.sh
qstone/generators/slurm/schedmd/type_exec_{app}.sbatch.jinja
qstone/multiprocessing/__init__.py
qstone/multiprocessing/mpi.py
qstone/multiprocessing/nompi.py
qstone/profiling/__init__.py
qstone/profiling/profile.py
qstone/utils/__init__.py
qstone/utils/config_schema.py
qstone/utils/utils.py
qstone-0.4.1.dist-info/LICENSE
qstone-0.4.1.dist-info/METADATA
qstone-0.4.1.dist-info/WHEEL
qstone-0.4.1.dist-info/entry_points.txt
qstone-0.4.1.dist-info/RECORD
