Metadata-Version: 2.1
Name: qstone
Version: 0.4.1
Summary: Benchmarking suite for Quantum Computers integration into HPC Systems
Home-page: https://github.com/riverlane/QStone
License: Apache 2.0
Keywords: Quantum,HPC
Author: Riverlane 
Author-email: team@riverlane.com
Requires-Python: >=3.10,<=3.13
Classifier: Development Status :: 4 - Beta
Classifier: License :: Other/Proprietary License
Classifier: Programming Language :: Python
Classifier: Programming Language :: Python :: 3
Classifier: Programming Language :: Python :: 3.10
Classifier: Programming Language :: Python :: 3.11
Classifier: Programming Language :: Python :: 3.12
Provides-Extra: docs
Provides-Extra: lint
Provides-Extra: mpi
Provides-Extra: security
Provides-Extra: test
Requires-Dist: PyMatching (>=2.2.1)
Requires-Dist: bandit ; extra == "security"
Requires-Dist: black ; extra == "lint"
Requires-Dist: click
Requires-Dist: cryptography (>=44.0.1)
Requires-Dist: flask
Requires-Dist: grpcio ; platform_machine == "amd64"
Requires-Dist: grpcio-tools ; extra == "test"
Requires-Dist: jinja2
Requires-Dist: json5
Requires-Dist: jsonschema
Requires-Dist: matplotlib
Requires-Dist: mpi4py ; extra == "mpi"
Requires-Dist: mypy ; extra == "lint"
Requires-Dist: myst_parser
Requires-Dist: nbsphinx ; extra == "docs"
Requires-Dist: numpy (>=1.22,<2.0)
Requires-Dist: ochrona ; extra == "security"
Requires-Dist: pandas-stubs
Requires-Dist: pandera
Requires-Dist: pip-audit
Requires-Dist: protobuf
Requires-Dist: pyGSTi (==0.9.13)
Requires-Dist: pylint ; extra == "lint"
Requires-Dist: pyquil
Requires-Dist: pytest ; extra == "test"
Requires-Dist: pytest-cov ; extra == "test"
Requires-Dist: pytest-depends ; extra == "test"
Requires-Dist: pytest-manual-marker ; extra == "test"
Requires-Dist: pytest-mock ; extra == "test"
Requires-Dist: qcs-sdk-python (>=0.21.12)
Requires-Dist: requests
Requires-Dist: requests-mock ; extra == "test"
Requires-Dist: safety ; extra == "security"
Requires-Dist: simple_slurm
Requires-Dist: sphinx ; extra == "docs"
Requires-Dist: sphinx-copybutton ; extra == "docs"
Requires-Dist: sphinx-mdinclude ; extra == "docs"
Requires-Dist: sphinx_rtd_theme ; extra == "docs"
Requires-Dist: stim (==1.14.0)
Requires-Dist: types-protobuf ; extra == "test"
Requires-Dist: waiting
Project-URL: Repository, https://github.com/riverlane/QStone
Project-URL: changelog, https://github.com/riverlane/QStone/blob/main/CHANGELOG.md
Project-URL: documentation, https://riverlane.github.io/QStone
